comicbot_api/__init__.py
comicbot_api/utils/__init__.py
comicbot_api/utils/comic.py
comicbot_api/utils/comic_release_builder.py
comicbot_api/utils/release_day.py
comicbot_api/v1/__init__.py
comicbot_api/v1/comic_bot_api_client.py
comicbot_api/v1/database/__init__.py
comicbot_api/v1/database/sqlite/DbClient.py
comicbot_api/v1/database/sqlite/__init__.py
comicbot_api/v1/database/sqlite/daos/__init__.py
comicbot_api/v1/database/sqlite/daos/comic_book.py
comicbot_api/v1/database/sqlite/sqlite.py
comicbot_api/v1/router/RequestRouter.py
comicbot_api/v1/router/__init__.py
comicbot_api/v1/static/__init__.py
comicbot_api/v1/static/types.py
comicbot_api/v1/validation.py
comicbot_api/v1/web_scraper.py
comicbot_api-0.1.19.dist-info/METADATA
comicbot_api-0.1.19.dist-info/WHEEL
comicbot_api-0.1.19.dist-info/RECORD
