Metadata-Version: 2.1
Name: comicbot-api
Version: 0.1.19
Summary: A client to retrieve new releases of comic books, filterable by publisher and format.
Author: Aaron Steed
Author-email: asteed7@gmail.com
Requires-Python: >=3.9,<4.0
Classifier: Programming Language :: Python :: 3
Classifier: Programming Language :: Python :: 3.9
Classifier: Programming Language :: Python :: 3.10
Classifier: Programming Language :: Python :: 3.11
Classifier: Programming Language :: Python :: 3.12
Classifier: Programming Language :: Python :: 3.13
Requires-Dist: beautifulsoup4 (==4.11.1)
Requires-Dist: loguru (>=0.7.2,<0.8.0)
Requires-Dist: lxml-html-clean (>=0.4.1,<0.5.0)
Requires-Dist: pyyaml (>=6.0,<7.0)
Requires-Dist: requests-html (>=0.10.0,<0.11.0)
Requires-Dist: ruff (>=0.9.7,<0.10.0)
Requires-Dist: sqlmodel (>=0.0.22,<0.0.23)
Requires-Dist: stealth-requests (>=1.2.1,<2.0.0)
